{"MaxDistance": 8.0, "Polyhedra": 288, "Not": 256, "Corner": 32, "Edge": 0, "Face": 0, "PolyConnect": [0, 0, 0, 1, 0, 0, 0, 0, 0, 0, 0, 0, 0, 0, 1, 0, 0, 1, 0, 0, 0, 0, 0, 1, 0, 0, 0, 0, 0, 0, 0, 0, 0, 0, 0, 0, 1, 0, 1, 0, 0, 1, 0, 0, 0, 0, 0, 0, 0, 0, 0, 0, 0, 0, 0, 0, 0, 1, 0, 0, 0, 0, 0, 0, 0, 0, 0, 0, 0, 0, 0, 0, 0, 0, 0, 1, 0, 0, 0, 0, 0, 0, 0, 1, 0, 0, 0, 0, 0, 0, 0, 0, 0, 0, 0, 0, 0, 0, 0, 0, 0, 0, 0, 0, 0, 0, 0, 0, 0, 0, 0, 0, 0, 0, 1, 0, 1, 1, 0, 0, 0, 0, 0, 0, 1, 0, 0, 1, 0, 0, 0, 1, 0, 0, 0, 0, 0, 0, 0, 0, 1, 0, 0, 0, 0, 0, 0, 0, 0, 0, 0, 0, 0, 0, 0, 0, 0, 0, 0, 1, 0, 1, 0, 0, 0, 0, 0, 0, 0, 0, 0, 0, 0, 0, 0, 0, 1, 0, 1, 0, 0, 1, 1, 0, 0, 0, 0, 0, 0, 0, 0, 0, 0, 0, 0, 0, 0, 0, 1, 0, 0, 0, 1, 0, 0, 0, 0, 0, 0, 0, 0, 0, 0, 0, 1, 0, 0, 0, 0, 0, 0, 0, 0, 0, 1, 0, 1, 0, 0, 0, 0, 0, 0, 0, 0, 0, 0, 0, 0, 0, 0, 0, 0, 1, 0, 0, 0, 0, 0, 0, 0, 0, 0, 0, 1, 0, 0, 0, 0, 0, 0, 0, 0, 0, 0, 0, 0, 1, 0, 0, 0, 0, 0, 0, 0, 0, 1, 0, 0, 0, 0, 0, 0, 0, 0, 0, 0, 0], "Additional": [{"valences": [4, 4], "CN": [4, 4], "cations": ["Si", "Si"], "distance": 7.487634791000338}, {"valences": [4, 4], "CN": [4, 4], "cations": ["Si", "Si"], "distance": 5.0648979907360445}, {"valences": [4, 4], "CN": [4, 4], "cations": ["Si", "Si"], "distance": 7.666174653408171}, {"valences": [4, 4], "CN": [4, 4], "cations": ["Si", "Si"], "distance": 3.167629652621544}, {"valences": [4, 4], "CN": [4, 4], "cations": ["Si", "Si"], "distance": 5.692201627565986}, {"valences": [4, 4], "CN": [4, 4], "cations": ["Si", "Si"], "distance": 4.578079627481375}, {"valences": [4, 4], "CN": [4, 4], "cations": ["Si", "Si"], "distance": 5.762621070863215}, {"valences": [4, 4], "CN": [4, 4], "cations": ["Si", "Si"], "distance": 7.936918338222886}, {"valences": [4, 4], "CN": [4, 4], "cations": ["Si", "Si"], "distance": 5.277377632333491}, {"valences": [4, 4], "CN": [4, 4], "cations": ["Si", "Si"], "distance": 5.172581430424214}, {"valences": [4, 4], "CN": [4, 4], "cations": ["Si", "Si"], "distance": 6.624592124430643}, {"valences": [4, 4], "CN": [4, 4], "cations": ["Si", "Si"], "distance": 7.367726636096115}, {"valences": [4, 4], "CN": [4, 4], "cations": ["Si", "Si"], "distance": 6.668321631782724}, {"valences": [4, 4], "CN": [4, 4], "cations": ["Si", "Si"], "distance": 7.408106702016419}, {"valences": [4, 4], "CN": [4, 4], "cations": ["Si", "Si"], "distance": 3.1725968996027847}, {"valences": [4, 4], "CN": [4, 4], "cations": ["Si", "Si"], "distance": 7.399277056067915}, {"valences": [4, 4], "CN": [4, 4], "cations": ["Si", "Si"], "distance": 5.12557708102931}, {"valences": [4, 4], "CN": [4, 4], "cations": ["Si", "Si"], "distance": 3.020946828018464}, {"valences": [4, 4], "CN": [4, 4], "cations": ["Si", "Si"], "distance": 7.075986946474002}, {"valences": [4, 4], "CN": [4, 4], "cations": ["Si", "Si"], "distance": 7.128155560009394}, {"valences": [4, 4], "CN": [4, 4], "cations": ["Si", "Si"], "distance": 5.03341224387663}, {"valences": [4, 4], "CN": [4, 4], "cations": ["Si", "Si"], "distance": 5.86745217399215}, {"valences": [4, 4], "CN": [4, 4], "cations": ["Si", "Si"], "distance": 7.83054499903809}, {"valences": [4, 4], "CN": [4, 4], "cations": ["Si", "Si"], "distance": 3.0414259090522924}, {"valences": [4, 4], "CN": [4, 4], "cations": ["Si", "Si"], "distance": 7.512686694637287}, {"valences": [4, 4], "CN": [4, 4], "cations": ["Si", "Si"], "distance": 6.893706371031008}, {"valences": [4, 4], "CN": [4, 4], "cations": ["Si", "Si"], "distance": 4.507284946365095}, {"valences": [4, 4], "CN": [4, 4], "cations": ["Si", "Si"], "distance": 5.814500355882167}, {"valences": [4, 4], "CN": [4, 4], "cations": ["Si", "Si"], "distance": 7.478120771963523}, {"valences": [4, 4], "CN": [4, 4], "cations": ["Si", "Si"], "distance": 7.124945566106627}, {"valences": [4, 4], "CN": [4, 4], "cations": ["Si", "Si"], "distance": 4.776719612372275}, {"valences": [4, 4], "CN": [4, 4], "cations": ["Si", "Si"], "distance": 7.129189397955201}, {"valences": [4, 4], "CN": [4, 4], "cations": ["Si", "Si"], "distance": 7.884635226106231}, {"valences": [4, 4], "CN": [4, 4], "cations": ["Si", "Si"], "distance": 7.640238875718767}, {"valences": [4, 4], "CN": [4, 4], "cations": ["Si", "Si"], "distance": 6.945754641645357}, {"valences": [4, 4], "CN": [4, 4], "cations": ["Si", "Si"], "distance": 7.487634791000337}, {"valences": [4, 4], "CN": [4, 4], "cations": ["Si", "Si"], "distance": 3.1104808838453306}, {"valences": [4, 4], "CN": [4, 4], "cations": ["Si", "Si"], "distance": 7.415524639893499}, {"valences": [4, 4], "CN": [4, 4], "cations": ["Si", "Si"], "distance": 3.1962891693290048}, {"valences": [4, 4], "CN": [4, 4], "cations": ["Si", "Si"], "distance": 4.47401240318805}, {"valences": [4, 4], "CN": [4, 4], "cations": ["Si", "Si"], "distance": 6.806502769377046}, {"valences": [4, 4], "CN": [4, 4], "cations": ["Si", "Si"], "distance": 3.058828375231773}, {"valences": [4, 4], "CN": [4, 4], "cations": ["Si", "Si"], "distance": 5.855278342119709}, {"valences": [4, 4], "CN": [4, 4], "cations": ["Si", "Si"], "distance": 7.145856978720865}, {"valences": [4, 4], "CN": [4, 4], "cations": ["Si", "Si"], "distance": 7.492449602580886}, {"valences": [4, 4], "CN": [4, 4], "cations": ["Si", "Si"], "distance": 7.3698565950665875}, {"valences": [4, 4], "CN": [4, 4], "cations": ["Si", "Si"], "distance": 7.1485371901044195}, {"valences": [4, 4], "CN": [4, 4], "cations": ["Si", "Si"], "distance": 4.920746485876146}, {"valences": [4, 4], "CN": [4, 4], "cations": ["Si", "Si"], "distance": 7.586801272660098}, {"valences": [4, 4], "CN": [4, 4], "cations": ["Si", "Si"], "distance": 6.4954288215216724}, {"valences": [4, 4], "CN": [4, 4], "cations": ["Si", "Si"], "distance": 5.186946903217171}, {"valences": [4, 4], "CN": [4, 4], "cations": ["Si", "Si"], "distance": 7.810332409293606}, {"valences": [4, 4], "CN": [4, 4], "cations": ["Si", "Si"], "distance": 7.3683454593866475}, {"valences": [4, 4], "CN": [4, 4], "cations": ["Si", "Si"], "distance": 5.766280485078275}, {"valences": [4, 4], "CN": [4, 4], "cations": ["Si", "Si"], "distance": 5.798504016000428}, {"valences": [4, 4], "CN": [4, 4], "cations": ["Si", "Si"], "distance": 4.8645079593717115}, {"valences": [4, 4], "CN": [4, 4], "cations": ["Si", "Si"], "distance": 5.428227115213161}, {"valences": [4, 4], "CN": [4, 4], "cations": ["Si", "Si"], "distance": 3.1759381840439977}, {"valences": [4, 4], "CN": [4, 4], "cations": ["Si", "Si"], "distance": 5.8116457542845685}, {"valences": [4, 4], "CN": [4, 4], "cations": ["Si", "Si"], "distance": 4.73442855430137}, {"valences": [4, 4], "CN": [4, 4], "cations": ["Si", "Si"], "distance": 7.026636957362494}, {"valences": [4, 4], "CN": [4, 4], "cations": ["Si", "Si"], "distance": 5.86745217399215}, {"valences": [4, 4], "CN": [4, 4], "cations": ["Si", "Si"], "distance": 4.968205798178196}, {"valences": [4, 4], "CN": [4, 4], "cations": ["Si", "Si"], "distance": 7.924522436796428}, {"valences": [4, 4], "CN": [4, 4], "cations": ["Si", "Si"], "distance": 7.444414671754841}, {"valences": [4, 4], "CN": [4, 4], "cations": ["Si", "Si"], "distance": 7.487634791000337}, {"valences": [4, 4], "CN": [4, 4], "cations": ["Si", "Si"], "distance": 4.800904783240523}, {"valences": [4, 4], "CN": [4, 4], "cations": ["Si", "Si"], "distance": 7.1485371901044195}, {"valences": [4, 4], "CN": [4, 4], "cations": ["Si", "Si"], "distance": 7.83245174793758}, {"valences": [4, 4], "CN": [4, 4], "cations": ["Si", "Si"], "distance": 5.875434352519708}, {"valences": [4, 4], "CN": [4, 4], "cations": ["Si", "Si"], "distance": 4.992019471672248}, {"valences": [4, 4], "CN": [4, 4], "cations": ["Si", "Si"], "distance": 7.5843612385204535}, {"valences": [4, 4], "CN": [4, 4], "cations": ["Si", "Si"], "distance": 5.896308016975354}, {"valences": [4, 4], "CN": [4, 4], "cations": ["Si", "Si"], "distance": 4.789177907798887}, {"valences": [4, 4], "CN": [4, 4], "cations": ["Si", "Si"], "distance": 7.989357600832522}, {"valences": [4, 4], "CN": [4, 4], "cations": ["Si", "Si"], "distance": 3.2061105770926397}, {"valences": [4, 4], "CN": [4, 4], "cations": ["Si", "Si"], "distance": 5.179876192283775}, {"valences": [4, 4], "CN": [4, 4], "cations": ["Si", "Si"], "distance": 5.067758266770008}, {"valences": [4, 4], "CN": [4, 4], "cations": ["Si", "Si"], "distance": 7.753746016096944}, {"valences": [4, 4], "CN": [4, 4], "cations": ["Si", "Si"], "distance": 5.658425262090611}, {"valences": [4, 4], "CN": [4, 4], "cations": ["Si", "Si"], "distance": 7.026636957362494}, {"valences": [4, 4], "CN": [4, 4], "cations": ["Si", "Si"], "distance": 4.272315620961809}, {"valences": [4, 4], "CN": [4, 4], "cations": ["Si", "Si"], "distance": 5.798350211353761}, {"valences": [4, 4], "CN": [4, 4], "cations": ["Si", "Si"], "distance": 3.0414259090522906}, {"valences": [4, 4], "CN": [4, 4], "cations": ["Si", "Si"], "distance": 7.512686694637283}, {"valences": [4, 4], "CN": [4, 4], "cations": ["Si", "Si"], "distance": 7.2664260958591615}, {"valences": [4, 4], "CN": [4, 4], "cations": ["Si", "Si"], "distance": 6.14637919631892}, {"valences": [4, 4], "CN": [4, 4], "cations": ["Si", "Si"], "distance": 7.92184082914969}, {"valences": [4, 4], "CN": [4, 4], "cations": ["Si", "Si"], "distance": 7.261152066256996}, {"valences": [4, 4], "CN": [4, 4], "cations": ["Si", "Si"], "distance": 5.173560739908733}, {"valences": [4, 4], "CN": [4, 4], "cations": ["Si", "Si"], "distance": 7.528894452943361}, {"valences": [4, 4], "CN": [4, 4], "cations": ["Si", "Si"], "distance": 7.366987994331297}, {"valences": [4, 4], "CN": [4, 4], "cations": ["Si", "Si"], "distance": 7.0352290275217735}, {"valences": [4, 4], "CN": [4, 4], "cations": ["Si", "Si"], "distance": 5.432038429628147}, {"valences": [4, 4], "CN": [4, 4], "cations": ["Si", "Si"], "distance": 7.7784123226592286}, {"valences": [4, 4], "CN": [4, 4], "cations": ["Si", "Si"], "distance": 7.487634791000338}, {"valences": [4, 4], "CN": [4, 4], "cations": ["Si", "Si"], "distance": 6.495428821521673}, {"valences": [4, 4], "CN": [4, 4], "cations": ["Si", "Si"], "distance": 5.186946903217171}, {"valences": [4, 4], "CN": [4, 4], "cations": ["Si", "Si"], "distance": 7.383644713704875}, {"valences": [4, 4], "CN": [4, 4], "cations": ["Si", "Si"], "distance": 4.973623949253697}, {"valences": [4, 4], "CN": [4, 4], "cations": ["Si", "Si"], "distance": 6.467363414012172}, {"valences": [4, 4], "CN": [4, 4], "cations": ["Si", "Si"], "distance": 6.450188761243506}, {"valences": [4, 4], "CN": [4, 4], "cations": ["Si", "Si"], "distance": 4.675423111855578}, {"valences": [4, 4], "CN": [4, 4], "cations": ["Si", "Si"], "distance": 7.5897177545234165}, {"valences": [4, 4], "CN": [4, 4], "cations": ["Si", "Si"], "distance": 5.323079646023052}, {"valences": [4, 4], "CN": [4, 4], "cations": ["Si", "Si"], "distance": 4.481418762642279}, {"valences": [4, 4], "CN": [4, 4], "cations": ["Si", "Si"], "distance": 6.668321631782723}, {"valences": [4, 4], "CN": [4, 4], "cations": ["Si", "Si"], "distance": 6.716550998815351}, {"valences": [4, 4], "CN": [4, 4], "cations": ["Si", "Si"], "distance": 5.283264645272921}, {"valences": [4, 4], "CN": [4, 4], "cations": ["Si", "Si"], "distance": 5.790293197025087}, {"valences": [4, 4], "CN": [4, 4], "cations": ["Si", "Si"], "distance": 4.8941172446799035}, {"valences": [4, 4], "CN": [4, 4], "cations": ["Si", "Si"], "distance": 7.867101812578405}, {"valences": [4, 4], "CN": [4, 4], "cations": ["Si", "Si"], "distance": 7.0700831472368675}, {"valences": [4, 4], "CN": [4, 4], "cations": ["Si", "Si"], "distance": 6.779458579758336}, {"valences": [4, 4], "CN": [4, 4], "cations": ["Si", "Si"], "distance": 3.1883224739487197}, {"valences": [4, 4], "CN": [4, 4], "cations": ["Si", "Si"], "distance": 5.205396453196011}, {"valences": [4, 4], "CN": [4, 4], "cations": ["Si", "Si"], "distance": 3.030994044047872}, {"valences": [4, 4], "CN": [4, 4], "cations": ["Si", "Si"], "distance": 3.1492835781379513}, {"valences": [4, 4], "CN": [4, 4], "cations": ["Si", "Si"], "distance": 6.8880309340736146}, {"valences": [4, 4], "CN": [4, 4], "cations": ["Si", "Si"], "distance": 7.266426095859161}, {"valences": [4, 4], "CN": [4, 4], "cations": ["Si", "Si"], "distance": 7.47812077196352}, {"valences": [4, 4], "CN": [4, 4], "cations": ["Si", "Si"], "distance": 7.124945566106622}, {"valences": [4, 4], "CN": [4, 4], "cations": ["Si", "Si"], "distance": 7.726125665690329}, {"valences": [4, 4], "CN": [4, 4], "cations": ["Si", "Si"], "distance": 7.487634791000335}, {"valences": [4, 4], "CN": [4, 4], "cations": ["Si", "Si"], "distance": 3.1759381840439986}, {"valences": [4, 4], "CN": [4, 4], "cations": ["Si", "Si"], "distance": 4.734428554301371}, {"valences": [4, 4], "CN": [4, 4], "cations": ["Si", "Si"], "distance": 7.444414671754841}, {"valences": [4, 4], "CN": [4, 4], "cations": ["Si", "Si"], "distance": 3.1104808838453306}, {"valences": [4, 4], "CN": [4, 4], "cations": ["Si", "Si"], "distance": 5.766280485078275}, {"valences": [4, 4], "CN": [4, 4], "cations": ["Si", "Si"], "distance": 5.0648979907360445}, {"valences": [4, 4], "CN": [4, 4], "cations": ["Si", "Si"], "distance": 7.666174653408169}, {"valences": [4, 4], "CN": [4, 4], "cations": ["Si", "Si"], "distance": 3.1962891693290043}, {"valences": [4, 4], "CN": [4, 4], "cations": ["Si", "Si"], "distance": 4.9682057981781975}, {"valences": [4, 4], "CN": [4, 4], "cations": ["Si", "Si"], "distance": 4.8645079593717115}, {"valences": [4, 4], "CN": [4, 4], "cations": ["Si", "Si"], "distance": 4.920746485876146}, {"valences": [4, 4], "CN": [4, 4], "cations": ["Si", "Si"], "distance": 7.810332409293606}, {"valences": [4, 4], "CN": [4, 4], "cations": ["Si", "Si"], "distance": 5.85527834211971}, {"valences": [4, 4], "CN": [4, 4], "cations": ["Si", "Si"], "distance": 5.798504016000428}, {"valences": [4, 4], "CN": [4, 4], "cations": ["Si", "Si"], "distance": 7.884635226106233}, {"valences": [4, 4], "CN": [4, 4], "cations": ["Si", "Si"], "distance": 7.3683454593866475}, {"valences": [4, 4], "CN": [4, 4], "cations": ["Si", "Si"], "distance": 3.0588283752317746}, {"valences": [4, 4], "CN": [4, 4], "cations": ["Si", "Si"], "distance": 7.924522436796429}, {"valences": [4, 4], "CN": [4, 4], "cations": ["Si", "Si"], "distance": 7.1458569787208654}, {"valences": [4, 4], "CN": [4, 4], "cations": ["Si", "Si"], "distance": 5.8116457542845685}, {"valences": [4, 4], "CN": [4, 4], "cations": ["Si", "Si"], "distance": 7.415524639893496}, {"valences": [4, 4], "CN": [4, 4], "cations": ["Si", "Si"], "distance": 5.428227115213162}, {"valences": [4, 4], "CN": [4, 4], "cations": ["Si", "Si"], "distance": 7.586801272660098}, {"valences": [4, 4], "CN": [4, 4], "cations": ["Si", "Si"], "distance": 7.492449602580886}, {"valences": [4, 4], "CN": [4, 4], "cations": ["Si", "Si"], "distance": 7.369856595066588}, {"valences": [4, 4], "CN": [4, 4], "cations": ["Si", "Si"], "distance": 7.487634791000335}, {"valences": [4, 4], "CN": [4, 4], "cations": ["Si", "Si"], "distance": 4.934512690668838}, {"valences": [4, 4], "CN": [4, 4], "cations": ["Si", "Si"], "distance": 4.997787492946543}, {"valences": [4, 4], "CN": [4, 4], "cations": ["Si", "Si"], "distance": 5.067758266770008}, {"valences": [4, 4], "CN": [4, 4], "cations": ["Si", "Si"], "distance": 7.753746016096945}, {"valences": [4, 4], "CN": [4, 4], "cations": ["Si", "Si"], "distance": 6.394887949232287}, {"valences": [4, 4], "CN": [4, 4], "cations": ["Si", "Si"], "distance": 7.281232533202981}, {"valences": [4, 4], "CN": [4, 4], "cations": ["Si", "Si"], "distance": 7.075986946474002}, {"valences": [4, 4], "CN": [4, 4], "cations": ["Si", "Si"], "distance": 7.128155560009393}, {"valences": [4, 4], "CN": [4, 4], "cations": ["Si", "Si"], "distance": 5.205396453196011}, {"valences": [4, 4], "CN": [4, 4], "cations": ["Si", "Si"], "distance": 3.0309940440478726}, {"valences": [4, 4], "CN": [4, 4], "cations": ["Si", "Si"], "distance": 4.660172773011831}, {"valences": [4, 4], "CN": [4, 4], "cations": ["Si", "Si"], "distance": 3.1003592310972783}, {"valences": [4, 4], "CN": [4, 4], "cations": ["Si", "Si"], "distance": 7.484633429707796}, {"valences": [4, 4], "CN": [4, 4], "cations": ["Si", "Si"], "distance": 7.4826868429970705}, {"valences": [4, 4], "CN": [4, 4], "cations": ["Si", "Si"], "distance": 6.369361197535342}, {"valences": [4, 4], "CN": [4, 4], "cations": ["Si", "Si"], "distance": 5.039123469348407}, {"valences": [4, 4], "CN": [4, 4], "cations": ["Si", "Si"], "distance": 7.921840829149688}, {"valences": [4, 4], "CN": [4, 4], "cations": ["Si", "Si"], "distance": 6.9029265412647005}, {"valences": [4, 4], "CN": [4, 4], "cations": ["Si", "Si"], "distance": 7.4608960330140635}, {"valences": [4, 4], "CN": [4, 4], "cations": ["Si", "Si"], "distance": 7.670992869359087}, {"valences": [4, 4], "CN": [4, 4], "cations": ["Si", "Si"], "distance": 4.3438740511325795}, {"valences": [4, 4], "CN": [4, 4], "cations": ["Si", "Si"], "distance": 6.319401463374237}, {"valences": [4, 4], "CN": [4, 4], "cations": ["Si", "Si"], "distance": 6.968134441574535}, {"valences": [4, 4], "CN": [4, 4], "cations": ["Si", "Si"], "distance": 7.739215331080984}, {"valences": [4, 4], "CN": [4, 4], "cations": ["Si", "Si"], "distance": 7.4876347910003345}, {"valences": [4, 4], "CN": [4, 4], "cations": ["Si", "Si"], "distance": 5.658425262090611}, {"valences": [4, 4], "CN": [4, 4], "cations": ["Si", "Si"], "distance": 3.2023902242807614}, {"valences": [4, 4], "CN": [4, 4], "cations": ["Si", "Si"], "distance": 5.033412243876631}, {"valences": [4, 4], "CN": [4, 4], "cations": ["Si", "Si"], "distance": 3.1492835781379513}, {"valences": [4, 4], "CN": [4, 4], "cations": ["Si", "Si"], "distance": 6.8880309340736146}, {"valences": [4, 4], "CN": [4, 4], "cations": ["Si", "Si"], "distance": 6.155651281049259}, {"valences": [4, 4], "CN": [4, 4], "cations": ["Si", "Si"], "distance": 3.1874875238267646}, {"valences": [4, 4], "CN": [4, 4], "cations": ["Si", "Si"], "distance": 3.118385894791198}, {"valences": [4, 4], "CN": [4, 4], "cations": ["Si", "Si"], "distance": 7.052566957942169}, {"valences": [4, 4], "CN": [4, 4], "cations": ["Si", "Si"], "distance": 5.039123469348406}, {"valences": [4, 4], "CN": [4, 4], "cations": ["Si", "Si"], "distance": 4.432915682904828}, {"valences": [4, 4], "CN": [4, 4], "cations": ["Si", "Si"], "distance": 7.261152066256996}, {"valences": [4, 4], "CN": [4, 4], "cations": ["Si", "Si"], "distance": 7.129189397955199}, {"valences": [4, 4], "CN": [4, 4], "cations": ["Si", "Si"], "distance": 6.968134441574536}, {"valences": [4, 4], "CN": [4, 4], "cations": ["Si", "Si"], "distance": 7.366987994331296}, {"valences": [4, 4], "CN": [4, 4], "cations": ["Si", "Si"], "distance": 7.40450450218727}, {"valences": [4, 4], "CN": [4, 4], "cations": ["Si", "Si"], "distance": 4.542474647951706}, {"valences": [4, 4], "CN": [4, 4], "cations": ["Si", "Si"], "distance": 4.521692779588376}, {"valences": [4, 4], "CN": [4, 4], "cations": ["Si", "Si"], "distance": 4.2945406437846}, {"valences": [4, 4], "CN": [4, 4], "cations": ["Si", "Si"], "distance": 7.778412322659227}, {"valences": [4, 4], "CN": [4, 4], "cations": ["Si", "Si"], "distance": 7.487634791000337}, {"valences": [4, 4], "CN": [4, 4], "cations": ["Si", "Si"], "distance": 4.789177907798887}, {"valences": [4, 4], "CN": [4, 4], "cations": ["Si", "Si"], "distance": 7.5288944529433595}, {"valences": [4, 4], "CN": [4, 4], "cations": ["Si", "Si"], "distance": 3.1676296526215446}, {"valences": [4, 4], "CN": [4, 4], "cations": ["Si", "Si"], "distance": 5.692201627565984}, {"valences": [4, 4], "CN": [4, 4], "cations": ["Si", "Si"], "distance": 4.800904783240523}, {"valences": [4, 4], "CN": [4, 4], "cations": ["Si", "Si"], "distance": 5.173560739908733}, {"valences": [4, 4], "CN": [4, 4], "cations": ["Si", "Si"], "distance": 3.206110577092639}, {"valences": [4, 4], "CN": [4, 4], "cations": ["Si", "Si"], "distance": 5.896308016975353}, {"valences": [4, 4], "CN": [4, 4], "cations": ["Si", "Si"], "distance": 5.798350211353761}, {"valences": [4, 4], "CN": [4, 4], "cations": ["Si", "Si"], "distance": 6.146379196318922}, {"valences": [4, 4], "CN": [4, 4], "cations": ["Si", "Si"], "distance": 5.432038429628146}, {"valences": [4, 4], "CN": [4, 4], "cations": ["Si", "Si"], "distance": 7.83245174793758}, {"valences": [4, 4], "CN": [4, 4], "cations": ["Si", "Si"], "distance": 4.992019471672248}, {"valences": [4, 4], "CN": [4, 4], "cations": ["Si", "Si"], "distance": 7.989357600832524}, {"valences": [4, 4], "CN": [4, 4], "cations": ["Si", "Si"], "distance": 5.875434352519711}, {"valences": [4, 4], "CN": [4, 4], "cations": ["Si", "Si"], "distance": 5.179876192283778}, {"valences": [4, 4], "CN": [4, 4], "cations": ["Si", "Si"], "distance": 7.584361238520456}, {"valences": [4, 4], "CN": [4, 4], "cations": ["Si", "Si"], "distance": 7.487634791000337}, {"valences": [4, 4], "CN": [4, 4], "cations": ["Si", "Si"], "distance": 3.1725968996027847}, {"valences": [4, 4], "CN": [4, 4], "cations": ["Si", "Si"], "distance": 7.399277056067913}, {"valences": [4, 4], "CN": [4, 4], "cations": ["Si", "Si"], "distance": 4.894117244679903}, {"valences": [4, 4], "CN": [4, 4], "cations": ["Si", "Si"], "distance": 7.867101812578405}, {"valences": [4, 4], "CN": [4, 4], "cations": ["Si", "Si"], "distance": 7.0700831472368675}, {"valences": [4, 4], "CN": [4, 4], "cations": ["Si", "Si"], "distance": 4.959524910259541}, {"valences": [4, 4], "CN": [4, 4], "cations": ["Si", "Si"], "distance": 4.602175385021408}, {"valences": [4, 4], "CN": [4, 4], "cations": ["Si", "Si"], "distance": 4.876897001025125}, {"valences": [4, 4], "CN": [4, 4], "cations": ["Si", "Si"], "distance": 7.859048566012508}, {"valences": [4, 4], "CN": [4, 4], "cations": ["Si", "Si"], "distance": 7.232233643693816}, {"valences": [4, 4], "CN": [4, 4], "cations": ["Si", "Si"], "distance": 3.100359231097278}, {"valences": [4, 4], "CN": [4, 4], "cations": ["Si", "Si"], "distance": 7.484633429707796}, {"valences": [4, 4], "CN": [4, 4], "cations": ["Si", "Si"], "distance": 3.187487523826766}, {"valences": [4, 4], "CN": [4, 4], "cations": ["Si", "Si"], "distance": 4.339609608932766}, {"valences": [4, 4], "CN": [4, 4], "cations": ["Si", "Si"], "distance": 6.55430683916945}, {"valences": [4, 4], "CN": [4, 4], "cations": ["Si", "Si"], "distance": 4.521692779588376}, {"valences": [4, 4], "CN": [4, 4], "cations": ["Si", "Si"], "distance": 7.4876347910003345}, {"valences": [4, 4], "CN": [4, 4], "cations": ["Si", "Si"], "distance": 4.578079627481376}, {"valences": [4, 4], "CN": [4, 4], "cations": ["Si", "Si"], "distance": 7.640238875718767}, {"valences": [4, 4], "CN": [4, 4], "cations": ["Si", "Si"], "distance": 5.125577081029309}, {"valences": [4, 4], "CN": [4, 4], "cations": ["Si", "Si"], "distance": 6.624592124430643}, {"valences": [4, 4], "CN": [4, 4], "cations": ["Si", "Si"], "distance": 6.893706371031006}, {"valences": [4, 4], "CN": [4, 4], "cations": ["Si", "Si"], "distance": 7.408106702016419}, {"valences": [4, 4], "CN": [4, 4], "cations": ["Si", "Si"], "distance": 4.776719612372274}, {"valences": [4, 4], "CN": [4, 4], "cations": ["Si", "Si"], "distance": 6.945754641645356}, {"valences": [4, 4], "CN": [4, 4], "cations": ["Si", "Si"], "distance": 5.762621070863216}, {"valences": [4, 4], "CN": [4, 4], "cations": ["Si", "Si"], "distance": 7.830544999038088}, {"valences": [4, 4], "CN": [4, 4], "cations": ["Si", "Si"], "distance": 5.277377632333492}, {"valences": [4, 4], "CN": [4, 4], "cations": ["Si", "Si"], "distance": 7.936918338222886}, {"valences": [4, 4], "CN": [4, 4], "cations": ["Si", "Si"], "distance": 3.020946828018464}, {"valences": [4, 4], "CN": [4, 4], "cations": ["Si", "Si"], "distance": 7.367726636096115}, {"valences": [4, 4], "CN": [4, 4], "cations": ["Si", "Si"], "distance": 5.172581430424214}, {"valences": [4, 4], "CN": [4, 4], "cations": ["Si", "Si"], "distance": 7.487634791000338}, {"valences": [4, 4], "CN": [4, 4], "cations": ["Si", "Si"], "distance": 6.7794585797583355}, {"valences": [4, 4], "CN": [4, 4], "cations": ["Si", "Si"], "distance": 5.323079646023051}, {"valences": [4, 4], "CN": [4, 4], "cations": ["Si", "Si"], "distance": 5.790293197025086}, {"valences": [4, 4], "CN": [4, 4], "cations": ["Si", "Si"], "distance": 7.726125665690333}, {"valences": [4, 4], "CN": [4, 4], "cations": ["Si", "Si"], "distance": 7.383644713704875}, {"valences": [4, 4], "CN": [4, 4], "cations": ["Si", "Si"], "distance": 6.450188761243506}, {"valences": [4, 4], "CN": [4, 4], "cations": ["Si", "Si"], "distance": 4.973623949253698}, {"valences": [4, 4], "CN": [4, 4], "cations": ["Si", "Si"], "distance": 3.188322473948721}, {"valences": [4, 4], "CN": [4, 4], "cations": ["Si", "Si"], "distance": 4.48141876264228}, {"valences": [4, 4], "CN": [4, 4], "cations": ["Si", "Si"], "distance": 4.6754231118555785}, {"valences": [4, 4], "CN": [4, 4], "cations": ["Si", "Si"], "distance": 6.467363414012175}, {"valences": [4, 4], "CN": [4, 4], "cations": ["Si", "Si"], "distance": 7.589717754523417}, {"valences": [4, 4], "CN": [4, 4], "cations": ["Si", "Si"], "distance": 7.48763479100034}, {"valences": [4, 4], "CN": [4, 4], "cations": ["Si", "Si"], "distance": 4.876897001025125}, {"valences": [4, 4], "CN": [4, 4], "cations": ["Si", "Si"], "distance": 7.859048566012508}, {"valences": [4, 4], "CN": [4, 4], "cations": ["Si", "Si"], "distance": 7.232233643693818}, {"valences": [4, 4], "CN": [4, 4], "cations": ["Si", "Si"], "distance": 6.5018254122296675}, {"valences": [4, 4], "CN": [4, 4], "cations": ["Si", "Si"], "distance": 5.4843345628544276}, {"valences": [4, 4], "CN": [4, 4], "cations": ["Si", "Si"], "distance": 7.4826868429970705}, {"valences": [4, 4], "CN": [4, 4], "cations": ["Si", "Si"], "distance": 6.369361197535342}, {"valences": [4, 4], "CN": [4, 4], "cations": ["Si", "Si"], "distance": 3.118385894791198}, {"valences": [4, 4], "CN": [4, 4], "cations": ["Si", "Si"], "distance": 7.052566957942171}, {"valences": [4, 4], "CN": [4, 4], "cations": ["Si", "Si"], "distance": 7.460896033014065}, {"valences": [4, 4], "CN": [4, 4], "cations": ["Si", "Si"], "distance": 7.6709928693590905}, {"valences": [4, 4], "CN": [4, 4], "cations": ["Si", "Si"], "distance": 7.487634791000339}, {"valences": [4, 4], "CN": [4, 4], "cations": ["Si", "Si"], "distance": 4.959524910259541}, {"valences": [4, 4], "CN": [4, 4], "cations": ["Si", "Si"], "distance": 4.339609608932765}, {"valences": [4, 4], "CN": [4, 4], "cations": ["Si", "Si"], "distance": 6.394887949232286}, {"valences": [4, 4], "CN": [4, 4], "cations": ["Si", "Si"], "distance": 7.281232533202981}, {"valences": [4, 4], "CN": [4, 4], "cations": ["Si", "Si"], "distance": 3.2023902242807614}, {"valences": [4, 4], "CN": [4, 4], "cations": ["Si", "Si"], "distance": 6.9029265412647005}, {"valences": [4, 4], "CN": [4, 4], "cations": ["Si", "Si"], "distance": 7.404504502187271}, {"valences": [4, 4], "CN": [4, 4], "cations": ["Si", "Si"], "distance": 7.487634791000335}, {"valences": [4, 4], "CN": [4, 4], "cations": ["Si", "Si"], "distance": 4.660172773011831}, {"valences": [4, 4], "CN": [4, 4], "cations": ["Si", "Si"], "distance": 6.155651281049259}, {"valences": [4, 4], "CN": [4, 4], "cations": ["Si", "Si"], "distance": 7.739215331080984}, {"valences": [4, 4], "CN": [4, 4], "cations": ["Si", "Si"], "distance": 4.542474647951704}, {"valences": [4, 4], "CN": [4, 4], "cations": ["Si", "Si"], "distance": 7.487634791000337}, {"valences": [4, 4], "CN": [4, 4], "cations": ["Si", "Si"], "distance": 4.934512690668838}, {"valences": [4, 4], "CN": [4, 4], "cations": ["Si", "Si"], "distance": 4.997787492946543}, {"valences": [4, 4], "CN": [4, 4], "cations": ["Si", "Si"], "distance": 7.487634791000337}], "cationvalences": [4, 4, 4, 4, 4, 4, 4, 4, 4, 4, 4, 4, 4, 4, 4, 4], "samevalences": true, "CNlist": [4, 4, 4, 4, 4, 4, 4, 4, 4, 4, 4, 4, 4, 4, 4, 4], "sameCN": true}