{"MaxDistance": 8.0, "Polyhedra": 282, "Not": 237, "Corner": 36, "Edge": 9, "Face": 0, "PolyConnect": [0, 1, 1, 0, 0, 0, 0, 0, 1, 1, 0, 0, 0, 1, 1, 0, 0, 0, 2, 0, 0, 0, 0, 0, 0, 0, 0, 0, 0, 0, 0, 0, 0, 2, 0, 0, 0, 0, 0, 0, 0, 0, 0, 0, 0, 0, 0, 1, 1, 0, 0, 0, 0, 0, 0, 0, 0, 0, 0, 0, 0, 0, 0, 0, 0, 0, 0, 0, 0, 1, 0, 0, 0, 2, 0, 0, 1, 0, 0, 0, 0, 0, 0, 0, 1, 0, 0, 1, 0, 0, 0, 0, 1, 0, 0, 0, 0, 0, 0, 0, 1, 0, 1, 0, 0, 0, 1, 0, 0, 0, 0, 0, 0, 0, 0, 0, 0, 0, 0, 0, 0, 1, 1, 0, 0, 0, 1, 1, 0, 0, 0, 0, 0, 0, 0, 0, 0, 1, 1, 0, 2, 0, 0, 0, 0, 2, 0, 0, 0, 0, 0, 0, 0, 0, 0, 0, 0, 0, 0, 0, 0, 0, 0, 0, 0, 0, 0, 0, 0, 0, 0, 1, 0, 0, 0, 0, 0, 2, 0, 0, 1, 0, 0, 0, 0, 1, 0, 0, 0, 0, 1, 0, 0, 0, 1, 0, 0, 0, 1, 0, 0, 0, 0, 0, 0, 0, 0, 2, 0, 0, 0, 0, 0, 1, 0, 0, 1, 0, 0, 0, 0, 0, 0, 1, 0, 1, 0, 0, 0, 0, 0, 1, 0, 0, 1, 0, 0, 0, 1, 1, 0, 0, 0, 2, 0, 0, 0, 2, 0, 0, 0, 0, 0, 0, 0, 0, 0, 0, 0, 0, 0, 0, 0, 0, 0, 0, 0, 0, 0, 0, 0, 0, 0, 0, 0, 0, 0, 0, 0, 0, 0, 0], "Additional": [{"valences": [3, 3], "CN": [6, 6], "cations": ["Sc", "Sc"], "distance": 4.864801160000001}, {"valences": [3, 3], "CN": [6, 6], "cations": ["Sc", "Sc"], "distance": 3.8401617534458263}, {"valences": [3, 3], "CN": [6, 6], "cations": ["Sc", "Sc"], "distance": 3.8401617534458263}, {"valences": [3, 3], "CN": [6, 6], "cations": ["Sc", "Sc"], "distance": 7.879049621959671}, {"valences": [3, 3], "CN": [6, 6], "cations": ["Sc", "Sc"], "distance": 5.445613215770834}, {"valences": [3, 3], "CN": [6, 6], "cations": ["Sc", "Sc"], "distance": 7.302122542255458}, {"valences": [3, 3], "CN": [6, 6], "cations": ["Sc", "Sc"], "distance": 6.4187282647916915}, {"valences": [3, 3], "CN": [6, 6], "cations": ["Sc", "Sc"], "distance": 6.4187282647916915}, {"valences": [3, 3], "CN": [6, 6], "cations": ["Sc", "Sc"], "distance": 3.8613636106625564}, {"valences": [3, 3], "CN": [6, 6], "cations": ["Sc", "Sc"], "distance": 3.8613636106625564}, {"valences": [3, 3], "CN": [6, 6], "cations": ["Sc", "Sc"], "distance": 7.889404894313872}, {"valences": [3, 3], "CN": [6, 6], "cations": ["Sc", "Sc"], "distance": 5.445612995198212}, {"valences": [3, 3], "CN": [6, 6], "cations": ["Sc", "Sc"], "distance": 7.302122377761756}, {"valences": [3, 6], "CN": [6, 6], "cations": ["Sc", "Te"], "distance": 3.553065649383657}, {"valences": [3, 6], "CN": [6, 6], "cations": ["Sc", "Te"], "distance": 3.553065649383657}, {"valences": [3, 6], "CN": [6, 6], "cations": ["Sc", "Te"], "distance": 7.743181268800622}, {"valences": [3, 6], "CN": [6, 6], "cations": ["Sc", "Te"], "distance": 6.71336489127802}, {"valences": [3, 6], "CN": [6, 6], "cations": ["Sc", "Te"], "distance": 6.71336489127802}, {"valences": [3, 6], "CN": [6, 6], "cations": ["Sc", "Te"], "distance": 3.14407089573542}, {"valences": [3, 6], "CN": [6, 6], "cations": ["Sc", "Te"], "distance": 5.778346802451334}, {"valences": [3, 6], "CN": [6, 6], "cations": ["Sc", "Te"], "distance": 5.727008869696368}, {"valences": [3, 6], "CN": [6, 6], "cations": ["Sc", "Te"], "distance": 7.52509809067407}, {"valences": [3, 3], "CN": [6, 6], "cations": ["Sc", "Sc"], "distance": 7.879049621959671}, {"valences": [3, 3], "CN": [6, 6], "cations": ["Sc", "Sc"], "distance": 7.302122542255458}, {"valences": [3, 3], "CN": [6, 6], "cations": ["Sc", "Sc"], "distance": 7.889404894313872}, {"valences": [3, 3], "CN": [6, 6], "cations": ["Sc", "Sc"], "distance": 7.302122377761756}, {"valences": [3, 6], "CN": [6, 6], "cations": ["Sc", "Te"], "distance": 7.743181268800622}, {"valences": [3, 6], "CN": [6, 6], "cations": ["Sc", "Te"], "distance": 5.8063458799916665}, {"valences": [3, 6], "CN": [6, 6], "cations": ["Sc", "Te"], "distance": 7.503515213922732}, {"valences": [3, 3], "CN": [6, 6], "cations": ["Sc", "Sc"], "distance": 5.4456129978657835}, {"valences": [3, 3], "CN": [6, 6], "cations": ["Sc", "Sc"], "distance": 7.3021223797511166}, {"valences": [3, 3], "CN": [6, 6], "cations": ["Sc", "Sc"], "distance": 6.418728268196382}, {"valences": [3, 3], "CN": [6, 6], "cations": ["Sc", "Sc"], "distance": 6.418728268196382}, {"valences": [3, 6], "CN": [6, 6], "cations": ["Sc", "Te"], "distance": 3.144065737964483}, {"valences": [3, 6], "CN": [6, 6], "cations": ["Sc", "Te"], "distance": 5.806343087118416}, {"valences": [3, 3], "CN": [6, 6], "cations": ["Sc", "Sc"], "distance": 7.3021223797511166}, {"valences": [3, 6], "CN": [6, 6], "cations": ["Sc", "Te"], "distance": 5.778343996045162}, {"valences": [3, 3], "CN": [6, 6], "cations": ["Sc", "Sc"], "distance": 6.35914716793715}, {"valences": [3, 3], "CN": [6, 6], "cations": ["Sc", "Sc"], "distance": 6.35914716793715}, {"valences": [3, 3], "CN": [6, 6], "cations": ["Sc", "Sc"], "distance": 7.613042959664755}, {"valences": [3, 3], "CN": [6, 6], "cations": ["Sc", "Sc"], "distance": 7.613042959664755}, {"valences": [3, 3], "CN": [6, 6], "cations": ["Sc", "Sc"], "distance": 4.4858788757108785}, {"valences": [3, 3], "CN": [6, 6], "cations": ["Sc", "Sc"], "distance": 6.617355938279764}, {"valences": [3, 6], "CN": [6, 6], "cations": ["Sc", "Te"], "distance": 7.464040835947453}, {"valences": [3, 3], "CN": [6, 6], "cations": ["Sc", "Sc"], "distance": 6.617355938279764}, {"valences": [3, 3], "CN": [6, 6], "cations": ["Sc", "Sc"], "distance": 4.485878873175663}, {"valences": [3, 3], "CN": [6, 6], "cations": ["Sc", "Sc"], "distance": 6.617355936561151}, {"valences": [3, 3], "CN": [6, 6], "cations": ["Sc", "Sc"], "distance": 3.861363609751648}, {"valences": [3, 3], "CN": [6, 6], "cations": ["Sc", "Sc"], "distance": 3.861363609751648}, {"valences": [3, 3], "CN": [6, 6], "cations": ["Sc", "Sc"], "distance": 7.88940489386804}, {"valences": [3, 3], "CN": [6, 6], "cations": ["Sc", "Sc"], "distance": 7.613042955230099}, {"valences": [3, 3], "CN": [6, 6], "cations": ["Sc", "Sc"], "distance": 7.613042955230099}, {"valences": [3, 3], "CN": [6, 6], "cations": ["Sc", "Sc"], "distance": 5.445613216470457}, {"valences": [3, 3], "CN": [6, 6], "cations": ["Sc", "Sc"], "distance": 7.302122542777208}, {"valences": [3, 6], "CN": [6, 6], "cations": ["Sc", "Te"], "distance": 5.727004865743218}, {"valences": [3, 6], "CN": [6, 6], "cations": ["Sc", "Te"], "distance": 7.503512157932145}, {"valences": [3, 6], "CN": [6, 6], "cations": ["Sc", "Te"], "distance": 7.464049145908093}, {"valences": [3, 3], "CN": [6, 6], "cations": ["Sc", "Sc"], "distance": 6.617355936561151}, {"valences": [3, 3], "CN": [6, 6], "cations": ["Sc", "Sc"], "distance": 7.88940489386804}, {"valences": [3, 3], "CN": [6, 6], "cations": ["Sc", "Sc"], "distance": 7.302122542777208}, {"valences": [3, 6], "CN": [6, 6], "cations": ["Sc", "Te"], "distance": 7.525095043448433}, {"valences": [3, 3], "CN": [6, 6], "cations": ["Sc", "Sc"], "distance": 4.86480116}, {"valences": [3, 3], "CN": [6, 6], "cations": ["Sc", "Sc"], "distance": 6.41872831504713}, {"valences": [3, 3], "CN": [6, 6], "cations": ["Sc", "Sc"], "distance": 4.842791016006352}, {"valences": [3, 3], "CN": [6, 6], "cations": ["Sc", "Sc"], "distance": 6.864321900308083}, {"valences": [3, 3], "CN": [6, 6], "cations": ["Sc", "Sc"], "distance": 4.842790864599974}, {"valences": [3, 3], "CN": [6, 6], "cations": ["Sc", "Sc"], "distance": 6.864321793490622}, {"valences": [3, 3], "CN": [6, 6], "cations": ["Sc", "Sc"], "distance": 5.690885978773537}, {"valences": [3, 3], "CN": [6, 6], "cations": ["Sc", "Sc"], "distance": 7.486819989136815}, {"valences": [3, 3], "CN": [6, 6], "cations": ["Sc", "Sc"], "distance": 3.8613635704361817}, {"valences": [3, 3], "CN": [6, 6], "cations": ["Sc", "Sc"], "distance": 7.889404874625612}, {"valences": [3, 6], "CN": [6, 6], "cations": ["Sc", "Te"], "distance": 5.561500317664374}, {"valences": [3, 6], "CN": [6, 6], "cations": ["Sc", "Te"], "distance": 7.38894959447676}, {"valences": [3, 6], "CN": [6, 6], "cations": ["Sc", "Te"], "distance": 3.2856345123356263}, {"valences": [3, 6], "CN": [6, 6], "cations": ["Sc", "Te"], "distance": 5.870407522054011}, {"valences": [3, 6], "CN": [6, 6], "cations": ["Sc", "Te"], "distance": 7.745885559255044}, {"valences": [3, 6], "CN": [6, 6], "cations": ["Sc", "Te"], "distance": 3.695034320983617}, {"valences": [3, 6], "CN": [6, 6], "cations": ["Sc", "Te"], "distance": 7.798953707490077}, {"valences": [3, 6], "CN": [6, 6], "cations": ["Sc", "Te"], "distance": 7.938444590612646}, {"valences": [3, 6], "CN": [6, 6], "cations": ["Sc", "Te"], "distance": 6.548582484226767}, {"valences": [3, 3], "CN": [6, 6], "cations": ["Sc", "Sc"], "distance": 6.41872831504713}, {"valences": [3, 3], "CN": [6, 6], "cations": ["Sc", "Sc"], "distance": 6.864321900308083}, {"valences": [3, 3], "CN": [6, 6], "cations": ["Sc", "Sc"], "distance": 6.864321793490622}, {"valences": [3, 3], "CN": [6, 6], "cations": ["Sc", "Sc"], "distance": 7.486819989136815}, {"valences": [3, 3], "CN": [6, 6], "cations": ["Sc", "Sc"], "distance": 3.8613635704361817}, {"valences": [3, 6], "CN": [6, 6], "cations": ["Sc", "Te"], "distance": 7.38894959447676}, {"valences": [3, 6], "CN": [6, 6], "cations": ["Sc", "Te"], "distance": 5.870407522054011}, {"valences": [3, 6], "CN": [6, 6], "cations": ["Sc", "Te"], "distance": 3.7169152516024875}, {"valences": [3, 6], "CN": [6, 6], "cations": ["Sc", "Te"], "distance": 7.928223140393998}, {"valences": [3, 6], "CN": [6, 6], "cations": ["Sc", "Te"], "distance": 6.536187894971602}, {"valences": [3, 3], "CN": [6, 6], "cations": ["Sc", "Sc"], "distance": 7.889404874625612}, {"valences": [3, 6], "CN": [6, 6], "cations": ["Sc", "Te"], "distance": 7.830084290390379}, {"valences": [3, 3], "CN": [6, 6], "cations": ["Sc", "Sc"], "distance": 3.8613635719453696}, {"valences": [3, 3], "CN": [6, 6], "cations": ["Sc", "Sc"], "distance": 7.889404875364264}, {"valences": [3, 3], "CN": [6, 6], "cations": ["Sc", "Sc"], "distance": 5.690885981989768}, {"valences": [3, 3], "CN": [6, 6], "cations": ["Sc", "Sc"], "distance": 7.486819991581539}, {"valences": [3, 3], "CN": [6, 6], "cations": ["Sc", "Sc"], "distance": 4.842791016661719}, {"valences": [3, 3], "CN": [6, 6], "cations": ["Sc", "Sc"], "distance": 6.864321900770446}, {"valences": [3, 6], "CN": [6, 6], "cations": ["Sc", "Te"], "distance": 7.7458855577859635}, {"valences": [3, 6], "CN": [6, 6], "cations": ["Sc", "Te"], "distance": 6.536192345630966}, {"valences": [3, 6], "CN": [6, 6], "cations": ["Sc", "Te"], "distance": 3.716917959129661}, {"valences": [3, 6], "CN": [6, 6], "cations": ["Sc", "Te"], "distance": 7.830085575644982}, {"valences": [3, 3], "CN": [6, 6], "cations": ["Sc", "Sc"], "distance": 3.8613635719453696}, {"valences": [3, 3], "CN": [6, 6], "cations": ["Sc", "Sc"], "distance": 7.486819991581539}, {"valences": [3, 3], "CN": [6, 6], "cations": ["Sc", "Sc"], "distance": 6.864321900770446}, {"valences": [3, 6], "CN": [6, 6], "cations": ["Sc", "Te"], "distance": 6.548586926462315}, {"valences": [3, 6], "CN": [6, 6], "cations": ["Sc", "Te"], "distance": 3.6950370445439753}, {"valences": [3, 3], "CN": [6, 6], "cations": ["Sc", "Sc"], "distance": 7.889404875364264}, {"valences": [3, 6], "CN": [6, 6], "cations": ["Sc", "Te"], "distance": 7.798954997874949}, {"valences": [3, 3], "CN": [6, 6], "cations": ["Sc", "Sc"], "distance": 7.613042841499928}, {"valences": [3, 3], "CN": [6, 6], "cations": ["Sc", "Sc"], "distance": 7.613042841499928}, {"valences": [3, 3], "CN": [6, 6], "cations": ["Sc", "Sc"], "distance": 7.613042838863438}, {"valences": [3, 3], "CN": [6, 6], "cations": ["Sc", "Sc"], "distance": 4.842790861594858}, {"valences": [3, 3], "CN": [6, 6], "cations": ["Sc", "Sc"], "distance": 6.864321791370507}, {"valences": [3, 3], "CN": [6, 6], "cations": ["Sc", "Sc"], "distance": 6.418728312366403}, {"valences": [3, 6], "CN": [6, 6], "cations": ["Sc", "Te"], "distance": 7.92821692961533}, {"valences": [3, 3], "CN": [6, 6], "cations": ["Sc", "Sc"], "distance": 7.613042838863438}, {"valences": [3, 3], "CN": [6, 6], "cations": ["Sc", "Sc"], "distance": 6.864321791370507}, {"valences": [3, 3], "CN": [6, 6], "cations": ["Sc", "Sc"], "distance": 6.418728312366403}, {"valences": [3, 6], "CN": [6, 6], "cations": ["Sc", "Te"], "distance": 7.938438387830913}, {"valences": [3, 3], "CN": [6, 6], "cations": ["Sc", "Sc"], "distance": 4.864801160000001}, {"valences": [3, 3], "CN": [6, 6], "cations": ["Sc", "Sc"], "distance": 3.861363512085851}, {"valences": [3, 3], "CN": [6, 6], "cations": ["Sc", "Sc"], "distance": 3.861363512085851}, {"valences": [3, 3], "CN": [6, 6], "cations": ["Sc", "Sc"], "distance": 7.889404846066824}, {"valences": [3, 3], "CN": [6, 6], "cations": ["Sc", "Sc"], "distance": 7.613043130282849}, {"valences": [3, 3], "CN": [6, 6], "cations": ["Sc", "Sc"], "distance": 7.613043130282849}, {"valences": [3, 3], "CN": [6, 6], "cations": ["Sc", "Sc"], "distance": 3.840161837544828}, {"valences": [3, 3], "CN": [6, 6], "cations": ["Sc", "Sc"], "distance": 3.840161837544828}, {"valences": [3, 3], "CN": [6, 6], "cations": ["Sc", "Sc"], "distance": 7.879049662948595}, {"valences": [3, 3], "CN": [6, 6], "cations": ["Sc", "Sc"], "distance": 6.359147366485246}, {"valences": [3, 3], "CN": [6, 6], "cations": ["Sc", "Sc"], "distance": 6.359147366485246}, {"valences": [3, 3], "CN": [6, 6], "cations": ["Sc", "Sc"], "distance": 5.445613043840906}, {"valences": [3, 3], "CN": [6, 6], "cations": ["Sc", "Sc"], "distance": 7.302122414037413}, {"valences": [3, 3], "CN": [6, 6], "cations": ["Sc", "Sc"], "distance": 4.485879039775115}, {"valences": [3, 3], "CN": [6, 6], "cations": ["Sc", "Sc"], "distance": 6.617356049498248}, {"valences": [3, 6], "CN": [6, 6], "cations": ["Sc", "Te"], "distance": 6.713365104576522}, {"valences": [3, 6], "CN": [6, 6], "cations": ["Sc", "Te"], "distance": 6.713365104576522}, {"valences": [3, 6], "CN": [6, 6], "cations": ["Sc", "Te"], "distance": 3.553065718429412}, {"valences": [3, 6], "CN": [6, 6], "cations": ["Sc", "Te"], "distance": 3.553065718429412}, {"valences": [3, 6], "CN": [6, 6], "cations": ["Sc", "Te"], "distance": 7.74318130048322}, {"valences": [3, 6], "CN": [6, 6], "cations": ["Sc", "Te"], "distance": 3.144074567723729}, {"valences": [3, 6], "CN": [6, 6], "cations": ["Sc", "Te"], "distance": 5.778348800427002}, {"valences": [3, 6], "CN": [6, 6], "cations": ["Sc", "Te"], "distance": 5.727000009424124}, {"valences": [3, 6], "CN": [6, 6], "cations": ["Sc", "Te"], "distance": 7.503508451380124}, {"valences": [3, 6], "CN": [6, 6], "cations": ["Sc", "Te"], "distance": 7.464047718707417}, {"valences": [3, 6], "CN": [6, 6], "cations": ["Sc", "Te"], "distance": 3.1440744399738447}, {"valences": [3, 6], "CN": [6, 6], "cations": ["Sc", "Te"], "distance": 5.806347799157618}, {"valences": [3, 6], "CN": [6, 6], "cations": ["Sc", "Te"], "distance": 5.726999811304853}, {"valences": [3, 6], "CN": [6, 6], "cations": ["Sc", "Te"], "distance": 7.525091196747817}, {"valences": [3, 6], "CN": [6, 6], "cations": ["Sc", "Te"], "distance": 7.464047924532414}, {"valences": [3, 3], "CN": [6, 6], "cations": ["Sc", "Sc"], "distance": 7.889404846066824}, {"valences": [3, 3], "CN": [6, 6], "cations": ["Sc", "Sc"], "distance": 7.879049662948595}, {"valences": [3, 3], "CN": [6, 6], "cations": ["Sc", "Sc"], "distance": 7.302122414037413}, {"valences": [3, 3], "CN": [6, 6], "cations": ["Sc", "Sc"], "distance": 6.617356049498248}, {"valences": [3, 6], "CN": [6, 6], "cations": ["Sc", "Te"], "distance": 7.74318130048322}, {"valences": [3, 6], "CN": [6, 6], "cations": ["Sc", "Te"], "distance": 5.806347868332797}, {"valences": [3, 6], "CN": [6, 6], "cations": ["Sc", "Te"], "distance": 7.525091347527257}, {"valences": [3, 6], "CN": [6, 6], "cations": ["Sc", "Te"], "distance": 5.778348730916634}, {"valences": [3, 6], "CN": [6, 6], "cations": ["Sc", "Te"], "distance": 7.503508300166986}, {"valences": [3, 3], "CN": [6, 6], "cations": ["Sc", "Sc"], "distance": 6.418728091310843}, {"valences": [3, 3], "CN": [6, 6], "cations": ["Sc", "Sc"], "distance": 6.418728091310843}, {"valences": [3, 3], "CN": [6, 6], "cations": ["Sc", "Sc"], "distance": 5.4456130404737095}, {"valences": [3, 3], "CN": [6, 6], "cations": ["Sc", "Sc"], "distance": 7.3021224115263}, {"valences": [3, 3], "CN": [6, 6], "cations": ["Sc", "Sc"], "distance": 7.3021224115263}, {"valences": [3, 3], "CN": [6, 6], "cations": ["Sc", "Sc"], "distance": 4.86480116}, {"valences": [3, 3], "CN": [6, 6], "cations": ["Sc", "Sc"], "distance": 4.842790819183268}, {"valences": [3, 3], "CN": [6, 6], "cations": ["Sc", "Sc"], "distance": 6.864321761449058}, {"valences": [3, 3], "CN": [6, 6], "cations": ["Sc", "Sc"], "distance": 4.842790821533013}, {"valences": [3, 3], "CN": [6, 6], "cations": ["Sc", "Sc"], "distance": 6.8643217631068065}, {"valences": [3, 3], "CN": [6, 6], "cations": ["Sc", "Sc"], "distance": 5.690886190125318}, {"valences": [3, 3], "CN": [6, 6], "cations": ["Sc", "Sc"], "distance": 7.486820149789656}, {"valences": [3, 3], "CN": [6, 6], "cations": ["Sc", "Sc"], "distance": 3.840161838844375}, {"valences": [3, 3], "CN": [6, 6], "cations": ["Sc", "Sc"], "distance": 7.87904966358198}, {"valences": [3, 3], "CN": [6, 6], "cations": ["Sc", "Sc"], "distance": 6.359147369553328}, {"valences": [3, 6], "CN": [6, 6], "cations": ["Sc", "Te"], "distance": 7.74588533080101}, {"valences": [3, 6], "CN": [6, 6], "cations": ["Sc", "Te"], "distance": 5.561500524210951}, {"valences": [3, 6], "CN": [6, 6], "cations": ["Sc", "Te"], "distance": 7.38894974993984}, {"valences": [3, 6], "CN": [6, 6], "cations": ["Sc", "Te"], "distance": 3.2856346343596354}, {"valences": [3, 6], "CN": [6, 6], "cations": ["Sc", "Te"], "distance": 5.8704075903501725}, {"valences": [3, 6], "CN": [6, 6], "cations": ["Sc", "Te"], "distance": 7.745885235730759}, {"valences": [3, 6], "CN": [6, 6], "cations": ["Sc", "Te"], "distance": 3.695037025729494}, {"valences": [3, 6], "CN": [6, 6], "cations": ["Sc", "Te"], "distance": 7.798954988960908}, {"valences": [3, 6], "CN": [6, 6], "cations": ["Sc", "Te"], "distance": 7.928223009407321}, {"valences": [3, 6], "CN": [6, 6], "cations": ["Sc", "Te"], "distance": 6.536187918175154}, {"valences": [3, 6], "CN": [6, 6], "cations": ["Sc", "Te"], "distance": 6.548586729816386}, {"valences": [3, 6], "CN": [6, 6], "cations": ["Sc", "Te"], "distance": 3.7169151658374}, {"valences": [3, 6], "CN": [6, 6], "cations": ["Sc", "Te"], "distance": 7.830084249677974}, {"valences": [3, 3], "CN": [6, 6], "cations": ["Sc", "Sc"], "distance": 6.864321761449058}, {"valences": [3, 3], "CN": [6, 6], "cations": ["Sc", "Sc"], "distance": 6.8643217631068065}, {"valences": [3, 3], "CN": [6, 6], "cations": ["Sc", "Sc"], "distance": 7.486820149789656}, {"valences": [3, 3], "CN": [6, 6], "cations": ["Sc", "Sc"], "distance": 3.840161838844375}, {"valences": [3, 3], "CN": [6, 6], "cations": ["Sc", "Sc"], "distance": 6.359147369553328}, {"valences": [3, 6], "CN": [6, 6], "cations": ["Sc", "Te"], "distance": 7.38894974993984}, {"valences": [3, 6], "CN": [6, 6], "cations": ["Sc", "Te"], "distance": 5.8704075903501725}, {"valences": [3, 6], "CN": [6, 6], "cations": ["Sc", "Te"], "distance": 3.7169179404259367}, {"valences": [3, 6], "CN": [6, 6], "cations": ["Sc", "Te"], "distance": 7.938444459794627}, {"valences": [3, 6], "CN": [6, 6], "cations": ["Sc", "Te"], "distance": 6.548582507386401}, {"valences": [3, 6], "CN": [6, 6], "cations": ["Sc", "Te"], "distance": 6.536192148612137}, {"valences": [3, 6], "CN": [6, 6], "cations": ["Sc", "Te"], "distance": 3.6950342347106524}, {"valences": [3, 3], "CN": [6, 6], "cations": ["Sc", "Sc"], "distance": 7.87904966358198}, {"valences": [3, 6], "CN": [6, 6], "cations": ["Sc", "Te"], "distance": 7.830085566766382}, {"valences": [3, 6], "CN": [6, 6], "cations": ["Sc", "Te"], "distance": 7.798953666615164}, {"valences": [3, 6], "CN": [6, 6], "cations": ["Sc", "Te"], "distance": 7.938438563931866}, {"valences": [3, 6], "CN": [6, 6], "cations": ["Sc", "Te"], "distance": 7.928217105943322}, {"valences": [3, 3], "CN": [6, 6], "cations": ["Sc", "Sc"], "distance": 4.86480116}, {"valences": [3, 3], "CN": [6, 6], "cations": ["Sc", "Sc"], "distance": 6.418728092034809}, {"valences": [3, 3], "CN": [6, 6], "cations": ["Sc", "Sc"], "distance": 7.6130431284846845}, {"valences": [3, 6], "CN": [6, 6], "cations": ["Sc", "Te"], "distance": 3.285634632502744}, {"valences": [3, 6], "CN": [6, 6], "cations": ["Sc", "Te"], "distance": 5.870407589310881}, {"valences": [3, 6], "CN": [6, 6], "cations": ["Sc", "Te"], "distance": 7.745885335724218}, {"valences": [3, 6], "CN": [6, 6], "cations": ["Sc", "Te"], "distance": 7.745885239184888}, {"valences": [3, 6], "CN": [6, 6], "cations": ["Sc", "Te"], "distance": 5.561500521067842}, {"valences": [3, 6], "CN": [6, 6], "cations": ["Sc", "Te"], "distance": 7.388949747574091}, {"valences": [3, 6], "CN": [6, 6], "cations": ["Sc", "Te"], "distance": 3.6950408930271386}, {"valences": [3, 6], "CN": [6, 6], "cations": ["Sc", "Te"], "distance": 7.798956821233796}, {"valences": [3, 6], "CN": [6, 6], "cations": ["Sc", "Te"], "distance": 7.928215274708873}, {"valences": [3, 6], "CN": [6, 6], "cations": ["Sc", "Te"], "distance": 3.7169218520186607}, {"valences": [3, 6], "CN": [6, 6], "cations": ["Sc", "Te"], "distance": 7.830087423588376}, {"valences": [3, 6], "CN": [6, 6], "cations": ["Sc", "Te"], "distance": 7.938436428136155}, {"valences": [3, 3], "CN": [6, 6], "cations": ["Sc", "Sc"], "distance": 6.418728092034809}, {"valences": [3, 3], "CN": [6, 6], "cations": ["Sc", "Sc"], "distance": 7.6130431284846845}, {"valences": [3, 6], "CN": [6, 6], "cations": ["Sc", "Te"], "distance": 5.870407589310881}, {"valences": [3, 6], "CN": [6, 6], "cations": ["Sc", "Te"], "distance": 7.388949747574091}, {"valences": [3, 6], "CN": [6, 6], "cations": ["Sc", "Te"], "distance": 3.7169217849574285}, {"valences": [3, 6], "CN": [6, 6], "cations": ["Sc", "Te"], "distance": 7.938436735055298}, {"valences": [3, 6], "CN": [6, 6], "cations": ["Sc", "Te"], "distance": 3.695040960485486}, {"valences": [3, 6], "CN": [6, 6], "cations": ["Sc", "Te"], "distance": 7.928214967394034}, {"valences": [3, 6], "CN": [6, 6], "cations": ["Sc", "Te"], "distance": 7.830087391754585}, {"valences": [3, 6], "CN": [6, 6], "cations": ["Sc", "Te"], "distance": 7.798956853194655}, {"valences": [3, 6], "CN": [6, 6], "cations": ["Sc", "Te"], "distance": 6.548578753584364}, {"valences": [3, 6], "CN": [6, 6], "cations": ["Sc", "Te"], "distance": 6.536184157254767}, {"valences": [3, 3], "CN": [6, 6], "cations": ["Sc", "Sc"], "distance": 3.8613635114875686}, {"valences": [3, 3], "CN": [6, 6], "cations": ["Sc", "Sc"], "distance": 7.889404845774002}, {"valences": [3, 6], "CN": [6, 6], "cations": ["Sc", "Te"], "distance": 6.536183937032122}, {"valences": [3, 3], "CN": [6, 6], "cations": ["Sc", "Sc"], "distance": 3.8613635114875686}, {"valences": [3, 6], "CN": [6, 6], "cations": ["Sc", "Te"], "distance": 6.548578533778537}, {"valences": [3, 3], "CN": [6, 6], "cations": ["Sc", "Sc"], "distance": 7.889404845774002}, {"valences": [3, 3], "CN": [6, 6], "cations": ["Sc", "Sc"], "distance": 4.864801160000001}, {"valences": [3, 6], "CN": [6, 6], "cations": ["Sc", "Te"], "distance": 3.5530657194963466}, {"valences": [3, 6], "CN": [6, 6], "cations": ["Sc", "Te"], "distance": 3.5530657194963466}, {"valences": [3, 6], "CN": [6, 6], "cations": ["Sc", "Te"], "distance": 7.743181300972798}, {"valences": [3, 6], "CN": [6, 6], "cations": ["Sc", "Te"], "distance": 6.7133651078725345}, {"valences": [3, 6], "CN": [6, 6], "cations": ["Sc", "Te"], "distance": 6.7133651078725345}, {"valences": [3, 6], "CN": [6, 6], "cations": ["Sc", "Te"], "distance": 3.144065636758093}, {"valences": [3, 6], "CN": [6, 6], "cations": ["Sc", "Te"], "distance": 5.778343940977561}, {"valences": [3, 6], "CN": [6, 6], "cations": ["Sc", "Te"], "distance": 5.727008644941878}, {"valences": [3, 6], "CN": [6, 6], "cations": ["Sc", "Te"], "distance": 7.50351504238034}, {"valences": [3, 6], "CN": [6, 6], "cations": ["Sc", "Te"], "distance": 3.144070922279227}, {"valences": [3, 6], "CN": [6, 6], "cations": ["Sc", "Te"], "distance": 5.8063458943648385}, {"valences": [3, 6], "CN": [6, 6], "cations": ["Sc", "Te"], "distance": 7.743181300972798}, {"valences": [3, 6], "CN": [6, 6], "cations": ["Sc", "Te"], "distance": 5.80634303231636}, {"valences": [3, 6], "CN": [6, 6], "cations": ["Sc", "Te"], "distance": 7.525097919623684}, {"valences": [3, 6], "CN": [6, 6], "cations": ["Sc", "Te"], "distance": 5.778346816894151}, {"valences": [3, 6], "CN": [6, 6], "cations": ["Sc", "Te"], "distance": 7.464049461114631}, {"valences": [3, 6], "CN": [6, 6], "cations": ["Sc", "Te"], "distance": 5.72700483910768}, {"valences": [3, 6], "CN": [6, 6], "cations": ["Sc", "Te"], "distance": 7.525095023177345}, {"valences": [3, 6], "CN": [6, 6], "cations": ["Sc", "Te"], "distance": 7.46404094532916}, {"valences": [3, 6], "CN": [6, 6], "cations": ["Sc", "Te"], "distance": 7.503512137602752}, {"valences": [6, 6], "CN": [6, 6], "cations": ["Te", "Te"], "distance": 4.86480116}, {"valences": [6, 6], "CN": [6, 6], "cations": ["Te", "Te"], "distance": 5.650343812737003}, {"valences": [6, 6], "CN": [6, 6], "cations": ["Te", "Te"], "distance": 5.664677174775842}, {"valences": [6, 6], "CN": [6, 6], "cations": ["Te", "Te"], "distance": 5.664677003720835}, {"valences": [6, 6], "CN": [6, 6], "cations": ["Te", "Te"], "distance": 5.650343984225924}, {"valences": [6, 6], "CN": [6, 6], "cations": ["Te", "Te"], "distance": 5.664670097559025}, {"valences": [6, 6], "CN": [6, 6], "cations": ["Te", "Te"], "distance": 5.650336889056355}, {"valences": [6, 6], "CN": [6, 6], "cations": ["Te", "Te"], "distance": 5.650336889056354}, {"valences": [6, 6], "CN": [6, 6], "cations": ["Te", "Te"], "distance": 5.664670097559024}, {"valences": [6, 6], "CN": [6, 6], "cations": ["Te", "Te"], "distance": 5.650343984225923}, {"valences": [6, 6], "CN": [6, 6], "cations": ["Te", "Te"], "distance": 5.664677003720834}, {"valences": [6, 6], "CN": [6, 6], "cations": ["Te", "Te"], "distance": 5.664677174775841}, {"valences": [6, 6], "CN": [6, 6], "cations": ["Te", "Te"], "distance": 5.650343812737002}, {"valences": [6, 6], "CN": [6, 6], "cations": ["Te", "Te"], "distance": 4.86480116}, {"valences": [6, 6], "CN": [6, 6], "cations": ["Te", "Te"], "distance": 5.10801474559752}, {"valences": [6, 6], "CN": [6, 6], "cations": ["Te", "Te"], "distance": 7.076896613366319}, {"valences": [6, 6], "CN": [6, 6], "cations": ["Te", "Te"], "distance": 5.107999419358012}, {"valences": [6, 6], "CN": [6, 6], "cations": ["Te", "Te"], "distance": 7.076885551087836}, {"valences": [6, 6], "CN": [6, 6], "cations": ["Te", "Te"], "distance": 7.030913472578253}, {"valences": [6, 6], "CN": [6, 6], "cations": ["Te", "Te"], "distance": 7.030902337950833}, {"valences": [6, 6], "CN": [6, 6], "cations": ["Te", "Te"], "distance": 5.107999609053716}, {"valences": [6, 6], "CN": [6, 6], "cations": ["Te", "Te"], "distance": 7.076885688007607}, {"valences": [6, 6], "CN": [6, 6], "cations": ["Te", "Te"], "distance": 7.030902475766082}, {"valences": [6, 6], "CN": [6, 6], "cations": ["Te", "Te"], "distance": 4.864801159999999}], "cationvalences": [3, 3, 3, 3, 3, 3, 6, 6, 6], "samevalences": false, "CNlist": [6, 6, 6, 6, 6, 6, 6, 6, 6], "sameCN": true}